Workbook

Sheet 说明与总览
A1: new-api 菲律宾部署方案 · 部署清单与 5 天落地计划（2 人全职）
A3: 项目信息
A4: 项目名称 | B4: new-api AI 网关（Go + React 单体二进制）· 菲律宾站部署
A5: 文档版本 | B5: v2.0
A6: 编制日期 | B6: 2026-09-22
A7: 编制依据 | B7: impl_deploy.md 第七章「阿里云部署方案（菲律宾 + 泰国）」7.1 – 7.10
A8: 主站点 | B8: 阿里云国际站 · 菲律宾 马尼拉 ap-southeast-6（承载菲律宾常态流量）
A9: 备 region | B9: 阿里云国际站 · 新加坡 ap-southeast-1（仅承载 PH 备工作负载，可与泰国备共用集群）
A10: 数据库策略 | B10: RDS PostgreSQL 高可用版【仅部署于马尼拉】；新加坡不部署任何数据库，备 region 经 RDS 公网地址 + TLS(verify-full) + IP 白名单读写马尼拉主库，不双写、无 DTS 链路
A11: 上游出口 | B11: 马尼拉 / 新加坡 NAT 固定 EIP 池 → 全球加速 GA → OpenAI / Anthropic / Google / Azure / AWS 等
A12: 目标 SLA | B12: ≥ 99.95%（月度不可用预算 21.6 分钟）
A13: 总工期 | B13: 5 个自然日（D1–D5）；2 人全职，合计 10 人日 / 80 人时
A14: 关键前提（门禁 G0） | B14: T-3 前置项（企业实名认证、资源配额审批、域名 NS 生效、证书签发、云产品开通）必须全部完成；任一项未完成则 5 天工期不可达，须顺延
A15: 工期风险等级 | B15: 高：无缓冲日、无人员冗余。已在「里程碑与验收」给出风险清单与裁剪预案
A17: 假设与关键参数（黄色底单元格需按实际情况确认/替换）
A18: 参数 | B18: 取值
A19: 部署启动日（D1，落地计划日期基准） | B19: 46287
A20: 前置启动日（T-3，账号/配额/域名/证书须在此日发起） | B20: 46287
A21: 投入人力 | B21: 2 人全职 —— 人员A：基础设施/网络/接入/SRE；人员B：数据/应用/CI-CD/DevOps
A22: 人力模型 | B22: 每时段（半天）= 2 人 × 4 小时 = 8 人时；单人每时段上限 4 人时；5 天共 10 个时段
A23: 业务域名（示例，需替换为正式域名） | B23: api.likha.com
A24: 运维域名（示例） | B24: ops.likha.com
A25: 镜像仓库前缀 | B25: registry-vpc.ap-southeast-6.aliyuncs.com/newapi/new-api
A26: 单实例规格 | B26: g8i.2xlarge（8 vCPU / 32 GiB）
A27: 日期口径：D1 = 部署启动日，落地计划中每项任务的日期均由此基准自动推算；任务均为「半天时段」粒度，D1上午 = 时段 S1 …… D5下午 = 时段 S10。数据来源：资源规格、数量与关键配置取自 impl_deploy.md 第 7.2 / 7.4 / 7.9 节；人时与配额为估算口径，需按实际情况与团队熟练度校准。
A29: 清单结构
A30: ① 账号与域名申请 | B30: 19 项前置申请：国际站注册与企业实名、支付与配额、RAM/MFA/审计、11 类云产品开通、域名实名与 NS 托管、SSL 证书、告警通道；标注【T-3 前置】与等待时长
A31: ② 资源清单-马尼拉 | B31: 菲律宾主站点（ap-southeast-6）29 项资源：网络、接入、计算、数据、缓存、日志、存储、安全、观测，以及 master / stable / canary 三个工作负载；含落地日（D1–D4）
A32: ③ 资源清单-新加坡 | B32: 备 region（ap-southeast-1）18 项资源：仅计算、接入与本地缓存/日志；【RDS 数量为 0，不部署】
A33: ④ 网络与安全规划 | B33: VPC/vSwitch 网段、EIP 规划、安全组逐条规则、KMS 凭据与轮换周期
A34: ⑤ 落地计划 | B34: 5 天 39 项任务，按 D1–D5 × 上午/下午共 10 个时段排布；含负责人员、前置依赖、人时、甘特条、验收标准，并附【T-3 前置门禁清单】与【人力负荷校验】（每时段单人 ≤ 4 人时）
A35: ⑥ 里程碑与验收 | B35: G0 门禁 + M1–M5 每日里程碑、验收证据、9 项关键风险、6 项工期裁剪预案

Sheet 账号与域名申请
A1: 阿里云国际站 · 账号、实名、配额与域名申请清单（★ = 阻塞 5 天工期的 T-3 前置项）
A3: 序号 | B3: 类别 | C3: 事项 | D3: 入口 / 平台 | E3: 关键要求与参数 | F3: 前置依赖 | G3: 负责角色 | H3: 启动时点 | I3: 工期 / 等待时长 | J3: 是否门禁项 | K3: 备注
A4: 1 | B4: 账号注册 | C4: 注册阿里云国际站账号 | D4: alibabacloud.com | E4: 企业域名邮箱注册；注册国家/地区选 Philippines；绑定可接收国际短信的手机号 | F4: — | G4: 项目负责人 | H4: T-3 前置 | I4: 0.5 工作日 | J4: ★ 门禁 | K4: 主账号仅用于计费与 RAM 管理，禁止日常运维使用
A5: 2 | B5: 账号注册 | C5: 完成企业实名认证 | D5: 阿里云国际站 · 实名认证 | E5: 提交菲律宾主体注册文件（DTI/SEC）、法人身份证件、公司地址证明；名称须与银行账户一致 | F5: 1 | G5: 项目负责人 | H5: T-3 前置 | I5: 1–2 工作日（等待） | J5: ★ 门禁 | K5: 未实名无法购买 ECS/RDS；5 天工期最大外部风险，须 T-3 立即提交并每日跟进
A6: 3 | B6: 账号注册 | C6: 开通后付费并绑定支付方式 | D6: 费用中心 · 支付方式 | E6: 绑定 Visa/MasterCard 企业卡或对公转账；开启自动扣款与余额告警 | F6: — | G6: 财务 | H6: T-3 前置 | I6: 0.5 工作日 | J6: ★ 门禁 | K6: 预留不低于 3 个月账单的信用额度，避免欠费停机
A7: 4 | B7: 账号安全 | C7: 主账号安全加固 | D7: 账号中心 · 安全设置 | E7: 开启 MFA、登录保护与异地登录告警；绑定安全邮箱与紧急联系人 | F7: 1 | G7: 安全负责人 | H7: T-3 前置 | I7: 0.5 工作日 | J7: — | K7: OWASP：主账号不做日常操作
A8: 5 | B8: 账号安全 | C8: 创建 RAM 用户与最小权限策略 | D8: RAM 控制台 | E8: 4 个角色：admin、ops、cicd-push（仅 ACR 推送）、iac-terraform（IaC 最小权限） | F8: 4 | G8: 安全负责人 | H8: T-3 前置 | I8: 0.5 工作日 | J8: ★ 门禁 | K8: 同时开启 ActionTrail，记录全部云 API 变更并保留 180 天
A9: 6 | B9: 账号安全 | C9: 配置资源组与成本标签 | D9: 资源管理 / 费用中心 | E9: 资源组按 site=ph-mnl、site=sg 划分；成本标签：项目、环境、站点、成本中心 | F9: 5 | G9: 运维负责人 | H9: T-3 前置 | I9: 0.5 工作日 | J9: — | K9: 用于分账、预算告警与成本核算
A10: 7 | B10: 配额申请 | C10: 提交资源配额（Quota）申请 | D10: 配额中心 / 工单 | E10: ECS vCPU ≥ 64（马尼拉）+ 32（新加坡）；ALB 2；EIP ≥ 10；RDS 16C64G；Tair 4GB 主备；ClickHouse 2 节点；OSS 2；GTM 1 | F10: 1 | G10: 运维负责人 | H10: T-3 前置 | I10: 2–3 工作日（等待） | J10: ★ 门禁 | K10: 国际站默认配额常不足；工单需说明业务场景与峰值，分两批（先马尼拉后新加坡）申请
A11: 8 | B11: 产品开通 | C11: 开通网络与计算类产品 | D11: 产品控制台 | E11: VPC、EIP、NAT 网关、ALB、ACK Pro 托管版、ACR 企业版 | F11: 1 | G11: 运维负责人 | H11: T-3 前置 | I11: 0.5 工作日 | J11: ★ 门禁 | K11: 国际站需逐个产品单独开通
A12: 9 | B12: 产品开通 | C12: 开通数据与缓存类产品 | D12: 产品控制台 | E12: RDS PostgreSQL（选 15）、Tair（Redis 兼容）、云数据库 ClickHouse（社区版 24.8） | F12: 1 | G12: 运维负责人 | H12: T-3 前置 | I12: 0.5 工作日 | J12: ★ 门禁 | K12: ClickHouse 仅承载 LOG_SQL_DSN，TTL 90 天
A13: 10 | B13: 产品开通 | C13: 开通接入与安全类产品 | D13: 产品控制台 | E13: 云解析 DNS（旗舰版）、GTM（旗舰版）、DCDN、WAF 3.0（企业版）、SSL 证书、KMS 凭据管家 | F13: 1 | G13: 运维负责人 | H13: T-3 前置 | I13: 0.5 工作日 | J13: ★ 门禁 | K13: WAF 需企业版；证书需在 D1 前完成签发
A14: 11 | B14: 产品开通 | C14: 开通可观测与审计类产品 | D14: 产品控制台 | E14: SLS、ARMS（Prometheus 版 + 应用监控）、云监控站点监控、ActionTrail | F14: 1 | G14: 运维负责人 | H14: T-3 前置 | I14: 0.5 工作日 | J14: — | K14: 拨测点选马尼拉、曼谷、新加坡、东京、香港
... A22: 19 | B22: 通知 | C22: 配置告警通道与联系人 | D22: 云监控 / ARMS | E22: 钉钉或企业微信机器人 + 短信 + 电话；P1 走电话并建立值班表 | F22: 11 | G22: 运维负责人 | H22: D3 下午 | I22: 见落地计划 #27 | J22: — | K22: 告警联系人须包含 2 名执行人与项目负责人
C24: ★ 门禁项共 11 项，全部为 T-3 前置（等待型）。G0 门禁未通过则 D1 不得启动，5 天工期不可达。

Sheet 资源清单-马尼拉
A1: 菲律宾主站点资源清单 · ap-southeast-6（马尼拉）
A3: 序号 | B3: 层 | C3: 资源 / 产品 | D3: 规格与版本 | E3: 数量 | F3: 命名规范 | G3: 地域 / 可用区 | H3: 关键配置 | I3: 前置依赖 | J3: 申请方式 | K3: 落地日 | L3: 负责 | M3: 备注
A4: 1 | B4: 网络 | C4: VPC | D4: 10.0.0.0/16 | E4: 1 | F4: vpc-newapi-mnl-prod | G4: ap-southeast-6 | H4: 单 VPC；开启 DNS 主机名解析；VPC 流日志投递 SLS | I4: — | J4: 控制台/IaC | K4: D1 | L4: 人员A | M4: 与新加坡网段不重叠
A5: 2 | B5: 网络 | C5: vSwitch（公共） | D5: 2 × /24 | E5: 2 | F5: vsw-mnl-pub-a / vsw-mnl-pub-b | G5: 可用区 A / B | H5: ALB 与 NAT 网关使用 | I5: 1 | J5: 控制台/IaC | K5: D1 | L5: 人员A | M5: 多可用区是高可用前提
A6: 3 | B6: 网络 | C6: vSwitch（私有） | D6: 4 × /20 | E6: 4 | F6: vsw-mnl-app-a/b、vsw-mnl-data-a/b | G6: 跨 2 个可用区 | H6: Pod 使用 app 网段，RDS 使用 data 网段 | I6: 1 | J6: 控制台/IaC | K6: D1 | L6: 人员A | M6: Pod 与数据库分网段便于隔离
A7: 4 | B7: 网络 | C7: NAT 网关 | D7: 多可用区 | E7: 1 | F7: nat-mnl-prod | G7: 跨 2 个可用区 | H7: 绑定固定 EIP 池；仅私有子网可出网 | I7: 1 | J7: 控制台/IaC | K7: D1 | L7: 人员A | M7: 供应商 IP 白名单依赖固定 EIP
A8: 5 | B8: 网络 | C8: EIP（上游出口白名单池） | D8: ≥ 4 个 | E8: 4 | F8: eip-mnl-upstream-01..04 | G8: 多可用区 | H8: 绑定 NAT 网关；用于供应商白名单与 GA 回源 | I8: 4 | J8: 控制台/IaC | K8: D1 | L8: 人员A | M8: 同一池也是备 region 访问 RDS 的白名单来源
A9: 6 | B9: 接入 | C9: ALB | D9: 标准版 II | E9: 1 | F9: alb-newapi-mnl | G9: 跨 2 个可用区 | H9: listeners 80（301）/ 443；idleTimeout=60s；requestTimeout=180s；TLS 1.2+1.3 | I9: 2,17 | J9: 控制台/IaC | K9: D3 | L9: 人员A | M9: SSE 靠网关 ping（15–20s）保活
A10: 7 | B10: 接入 | C10: WAF 3.0 | D10: 企业版 | E10: 1 | F10: waf-newapi-mnl | G10: 马尼拉 | H10: 接入 api.example-ph.com；CC 阈值对齐 GLOBAL_API_RATE_LIMIT；放行支付回调 | I10: 6 | J10: 控制台 | K10: D3 | L10: 人员A | M10: 抗 L7
A11: 8 | B11: 接入 | C11: 云解析 DNS | D11: 旗舰版 | E11: 1 | F11: — | G11: 全球 | H11: 承载主域名与子域名解析 | I11: 15(前置) | J11: 控制台 | K11: D1 | L11: 人员A | M11: 与 GTM 配合完成按延迟解析
A12: 9 | B12: 接入 | C12: 全局流量管理 GTM | D12: 旗舰版 | E12: 1 | F12: gtm-newapi-ph | G12: 全球 | H12: 主地址池 = 马尼拉 ALB；备地址池 = 新加坡 ALB；探测 /api/status 每 15s | I12: 6,17(前置) | J12: 控制台 | K12: D3 | L12: 人员A | M12: 故障切换目标 ≤ 60s
A13: 10 | B13: 接入 | C13: DCDN | D13: 按量付费 | E13: 1 | F13: dcdn-newapi-ph | G13: 全球 | H13: 静态资源加速；index.html no-cache；带指纹 chunk 缓存 7 天 | I13: 17(前置) | J13: 控制台 | K13: D2 | L13: 人员A | M13: 可按裁剪预案延后
A14: 11 | B14: 计算 | C14: ACK Pro 托管版 | D14: 控制面 SLA 99.95% | E14: 1 | F14: ack-newapi-mnl | G14: 多可用区 | H14: Kubernetes 1.31+；CNI Terway；开启 RRSA | I14: 7(前置) | J14: 控制台 | K14: D2 | L14: 人员A | M14: 需 ACK 配额已批复
A15: 12 | B15: 计算 | C15: ECS 节点池 | D15: g8i.2xlarge（8C32G） | E15: ≥ 4 | F15: ecs-mnl-node-01..04 | G15: 跨 2 个可用区 | H15: 系统盘 100G ESSD PL1 + 数据盘 300G ESSD；nofile=200000 | I15: 11 | J15: 控制台 | K15: D2 | L15: 人员A | M15: HPA min 4 / max 16；单 AZ 故障仍有 2 副本
A16: 13 | B16: 计算 | C16: ACR 企业版（马尼拉） | D16: 企业版实例 | E16: 1 | F16: acr-newapi-mnl | G16: ap-southeast-6 | H16: VPC 域名供集群拉取；开启镜像扫描与签名 | I16: 12(前置) | J16: 控制台 | K16: D2 | L16: 人员B | M16: 镜像 tag = git sha
A17: 14 | B17: 数据 | C17: RDS PostgreSQL 高可用版 | D17: pg 15，16C64G | E17: 1 | F17: rds-mnl-newapi | G17: 主 A 备 B（跨可用区） | H17: PITR 7 天；每日全量 + WAL 归档 OSS；开启公网地址但仅放行新加坡 NAT EIP | I17: 9(前置) | J17: 控制台/IaC | K17: D1 | L17: 人员B | M17: 菲律宾唯一主库
A18: 15 | B18: 数据 | C18: RDS 账号与数据库 | D18: — | E18: 2 | F18: newapi / newapi_sg | G18: 马尼拉 | H18: newapi：应用主账号；newapi_sg：备 region 接管账号（最小权限） | I18: 14 | J18: 控制台 | K18: D2 | L18: 人员B | M18: 禁止与备 region 共用超级账号
A19: 16 | B19: 数据 | C19: RDS 只读实例（可选） | D19: pg 15，同规格 | E19: 1 | F19: rds-mnl-newapi-ro | G19: 马尼拉 | H19: 报表与导出类查询分流 | I19: 14 | J19: 控制台 | K19: D2 | L19: 人员B | M19: 非必需，工期/成本紧张时按裁剪预案取消
A20: 17 | B20: 缓存 | C20: Tair（Redis 兼容） | D20: 主备版 4 GB | E20: 1 | F20: tair-mnl-newapi | G20: 多可用区 | H20: 密码 + 内网 ACL；maxmemory-policy allkeys-lru | I20: 4(前置) | J20: 控制台 | K20: D1 | L20: 人员B | M20: 生产建议升级集群版
A21: 18 | B21: 日志 | C21: 云数据库 ClickHouse | D21: 社区版 24.8，2 节点 | E21: 1 | F21: ck-mnl-newapi | G21: 马尼拉 | H21: 仅承载 LOG_SQL_DSN；TTL 90 天 | I21: 9(前置) | J21: 控制台 | K21: D1 | L21: 人员B | M21: 写日志失败必须降级
A22: 19 | B22: 存储 | C22: OSS Bucket | D22: 标准 + 低频生命周期 | E22: 1 | F22: oss-newapi-mnl | G22: 马尼拉 | H22: 同城冗余 ZRS；版本控制；90 天转归档；防盗链 + 签名 URL | I22: 12(前置) | J22: 控制台 | K22: D1 | L22: 人员B | M22: 同时承载 RDS 备份归档
A23: 20 | B23: 安全 | C23: KMS 凭据管家 | D23: 软件密钥 | E23: 1 | F23: kms-newapi-mnl | G23: 马尼拉 | H23: 托管 SQL_DSN、REDIS_CONN_STRING、SESSION_SECRET、支付渠道密钥 | I23: 10(前置) | J23: 控制台 | K23: D2 | L23: 人员B | M23: 经 RRSA + ExternalSecret 注入，密钥不落 Git
A24: 21 | B24: 安全 | C24: 安全组与网络 ACL | D24: — | E24: — | F24: sg-mnl-alb / sg-mnl-app / sg-mnl-db | G24: 马尼拉 | H24: 端口最小化，规则详见「网络与安全规划」 | I24: 2,3,12 | J24: 控制台 | K24: D3 | L24: 人员A | M24: app 仅允许 ALB 访问 3000
A25: 22 | B25: 观测 | C25: SLS Project / LogStore | D25: 按量 | E25: 1 | F25: sls-newapi-mnl | G25: 马尼拉 | H25: 采集 /app/logs 与 stdout；sys 30 天 / audit 180 天 | I25: 11 | J25: 控制台 | K25: D4 | L25: 人员A | M25: Logtail DaemonSet 采集
A26: 23 | B26: 观测 | C26: ARMS Prometheus + 应用监控 | D26: 按量 | E26: 1 | F26: arms-newapi-mnl | G26: 马尼拉 | H26: ServiceMonitor 抓 /metrics（需补建）；OpenTelemetry SDK（需补建） | I26: 11 | J26: 控制台 | K26: D4 | L26: 人员A | M26: 代码补建项须在 T-3 完成，否则临时用 /api/status 拨测
A27: 24 | B27: 观测 | C27: 云监控站点监控（拨测） | D27: 按量 | E27: 1 | F27: — | G27: 马尼拉 + 新加坡 + 东京 + 香港 | H27: 探测 GET /api/status，间隔 1 分钟，断言 success:true 与版本匹配 | I27: 11(前置) | J27: 控制台 | K27: D4 | L27: 人员A | M27: 真实用户视角可用性
A28: 25 | B28: 观测 | C28: 操作审计 ActionTrail | D28: 默认 | E28: 1 | F28: — | G28: 马尼拉 | H28: 记录全部云 API 变更，保留 180 天 | I28: 5(前置) | J28: 控制台 | K28: D1 | L28: 人员A | M28: 合规与变更追溯
A29: 26 | B29: 工作负载 | C29: master Deployment | D29: — | E29: 1 | F29: new-api-master | G29: 马尼拉 | H29: NODE_TYPE=master；replicas=1；Recreate；独立 PVC（RWO）；不接 ALB 流量 | I29: 11,14 | J29: GitOps | K29: D2 | L29: 人员B | M29: 唯一执行 AutoMigrate 与 master-only 任务的节点
A30: 27 | B30: 工作负载 | C30: stable Deployment | D30: — | E30: 1 | F30: new-api-stable | G30: 跨 2 个可用区 | H30: replicas=4；maxUnavailable=0；PDB minAvailable=3；HPA 4–16；preStop sleep 15s | I30: 26 | J30: GitOps | K30: D3 | L30: 人员B | M30: 滚动发布零停机是 99.95% 前提
A31: 28 | B31: 工作负载 | C31: canary Deployment | D31: — | E31: 1 | F31: new-api-canary | G31: 马尼拉 | H31: replicas=1；独立 Service 与 Ingress；canary-weight 5→20→50→100 | I31: 26 | J31: GitOps | K31: D4 | L31: 人员B | M31: 灰度失败可秒级归零
A32: 29 | B32: 工作负载 | C32: Namespace / ConfigMap / Secret | D32: — | E32: 1 | F32: namespace: new-api | G32: 马尼拉 | H32: 见 impl_deploy.md 7.4.1；密钥由 KMS + ExternalSecret 注入 | I32: 20,11 | J32: GitOps | K32: D2 | L32: 人员B | M32: SESSION_SECRET 必须全区域一致

Sheet 资源清单-新加坡
A1: 备 region 资源清单 · ap-southeast-1（新加坡，仅承载菲律宾备用负载）
A3: 序号 | B3: 层 | C3: 资源 / 产品 | D3: 规格与版本 | E3: 数量 | F3: 命名规范 | G3: 地域 / 可用区 | H3: 关键配置 | I3: 前置依赖 | J3: 申请方式 | K3: 落地日 | L3: 负责 | M3: 备注
A4: 1 | B4: 网络 | C4: VPC | D4: 10.1.0.0/16 | E4: 1 | F4: vpc-newapi-sg-prod | G4: ap-southeast-1 | H4: 独立 VPC；不部署任何数据库实例 | I4: — | J4: 控制台/IaC | K4: D2 | L4: 人员A | M4: 网段与马尼拉不重叠
A5: 2 | B5: 网络 | C5: vSwitch | D5: 4 × /20 | E5: 4 | F5: vsw-sg-pub-a/b、vsw-sg-app-a/b | G5: 跨 2 个可用区 | H5: 公共子网承载 ALB 与 NAT；私有子网承载 Pod | I5: 1 | J5: 控制台/IaC | K5: D2 | L5: 人员A | M5: 至少 2 个可用区
A6: 3 | B6: 网络 | C6: NAT 网关 + EIP 池 | D6: ≥ 4 个 EIP | E6: 4 | F6: nat-sg-prod / eip-sg-upstream-01..04 | G6: 多可用区 | H6: 固定 EIP 两用：① 上游出口白名单；② 马尼拉 RDS 公网白名单来源 | I6: 1 | J6: 控制台/IaC | K6: D2 | L6: 人员A | M6: 关键：这批 EIP 必须加入马尼拉 RDS 白名单，禁止 0.0.0.0/0
A7: 4 | B7: 接入 | C7: ALB | D7: 标准版 II | E7: 1 | F7: alb-newapi-sg | G7: 跨 2 个可用区 | H7: 与马尼拉同配置：443 + idleTimeout 60s + requestTimeout 180s | I7: 3,17(前置) | J7: 控制台/IaC | K7: D4 | L7: 人员A | M7: GTM 接管时直接解析到该 ALB
A8: 5 | B8: 接入 | C8: WAF 3.0 | D8: 企业版 | E8: 1 | F8: waf-newapi-sg | G8: 新加坡 | H8: 接管时承接 api.example-ph.com 流量；规则与马尼拉保持一致 | I8: 4 | J8: 控制台 | K8: D4 | L8: 人员A | M8: 规则差异会导致切换后行为不一致
A9: 6 | B9: 接入 | C9: ACR 企业版（新加坡） | D9: 企业版实例 | E9: 1 | F9: acr-newapi-sg | G9: ap-southeast-1 | H9: 提供新加坡 VPC 域名，供备 region 节点拉取同一镜像 | I9: 12(前置) | J9: 控制台 | K9: D2 | L9: 人员B | M9: 避免跨区拉镜像
A10: 7 | B10: 计算 | C10: ACK Pro 托管版 | D10: 控制面 SLA 99.95% | E10: 1 | F10: ack-newapi-sg | G10: 多可用区 | H10: 与马尼拉同构；后续泰国备可复用该集群（独立 Deployment） | I10: 1 | J10: 控制台 | K10: D4 | L10: 人员A | M10: 不同站点备负载必须互相隔离
A11: 8 | B11: 计算 | C11: ECS 节点池 | D11: g8i.2xlarge（8C32G） | E11: ≥ 2 | F11: ecs-sg-node-01..02 | G11: 跨 2 个可用区 | H11: PH 备 2 副本；冷备形态可置 0 并预留扩容预案 | I11: 7 | J11: 控制台 | K11: D4 | L11: 人员A | M11: 冷备会牺牲 RTO（秒级 → 分钟级）
A12: 9 | B12: 数据 | C12: RDS PostgreSQL | D12: — | E12: 0 | F12: — | G12: 新加坡 | H12: 【不部署】备 region 直接使用马尼拉 RDS 的公网地址 | I12: — | J12: — | K12: D1 | L12: 人员B | M12: 红线：禁止本地库、只读副本、DTS 双向链路
A13: 10 | B13: 数据 | C13: RDS 公网白名单 | D13: — | E13: 1 | F13: — | G13: 马尼拉 RDS | H13: 仅加入新加坡 NAT EIP；仅开放 5432；应用侧 sslmode=verify-full + RDS CA 校验 | I13: 3,14(马尼拉) | J13: 控制台 | K13: D2 | L13: 人员B | M13: 连接串不得出现 sslmode=disable / require
A14: 11 | B14: 缓存 | C14: Tair（Redis 兼容） | D14: 主备版 4 GB | E14: 1 | F14: tair-sg-newapi | G14: 多可用区 | H14: 备 region 本地缓存与限流；不跨区访问马尼拉 Tair | I14: 1 | J14: 控制台 | K14: D4 | L14: 人员B | M14: 跨区缓存会放大延迟与故障面
A15: 12 | B15: 日志 | C15: 云数据库 ClickHouse | D15: 社区版 24.8，2 节点 | E15: 1 | F15: ck-sg-newapi | G15: 新加坡 | H15: 备 region 本地日志库，避免跨区写日志 | I15: 1 | J15: 控制台 | K15: D4 | L15: 人员B | M15: 工期紧张时按裁剪预案暂用主站点
A16: 13 | B16: 存储 | C16: OSS Bucket | D16: 标准 + 低频生命周期 | E16: 1 | F16: oss-newapi-sg | G16: 新加坡 | H16: 版本控制 + 90 天转归档 | I16: 1 | J16: 控制台 | K16: D2 | L16: 人员B | M16: DCDN 回源可指向本 bucket
A17: 14 | B17: 安全 | C17: 安全组 | D17: — | E17: — | F17: sg-sg-alb / sg-sg-app | G17: 新加坡 | H17: alb 入向 443/80；app 入向 3000 仅来自 alb-sg；app 出向允许访问马尼拉 RDS 公网 5432 | I17: 2,10 | J17: 控制台 | K17: D4 | L17: 人员A | M17: 出向按目的地址精确放行
A18: 15 | B18: 工作负载 | C18: PH 备 Deployment | D18: — | E18: 1 | F18: new-api-ph-standby | G18: 跨 2 个可用区 | H18: replicas=2；NODE_TYPE=slave；track=standby；site=ph；SQL_MAX_OPEN_CONNS=150 | I18: 7,11 | J18: GitOps | K18: D4 | L18: 人员B | M18: 必须固定 slave，避免与马尼拉 master 并发迁移同一 schema
A19: 16 | B19: 工作负载 | C19: 备 region Secret | D19: — | E19: 1 | F19: new-api-secret-sg-ph | G19: 新加坡 | H19: SQL_DSN 指向马尼拉 RDS 公网地址；SESSION_SECRET 与主站点完全一致 | I19: 20(马尼拉) | J19: GitOps | K19: D4 | L19: 人员B | M19: 同 SESSION_SECRET 保证接管瞬间会话与令牌不失效
A20: 17 | B20: 观测 | C20: SLS / ARMS 接入 | D20: 按量 | E20: 1 | F20: sls-newapi-sg / arms-newapi-sg | G20: 新加坡 | H20: 与应用同构采集；备 region 日志单独 LogStore | I20: 7 | J20: 控制台 | K20: D4 | L20: 人员A | M20: 告警通道复用主站点值班表
A21: 18 | B21: 观测 | C21: 备 region 链路拨测 | D21: 按量 | E21: 1 | F21: — | G21: 新加坡 → 马尼拉 | H21: 对马尼拉 RDS 公网地址做 TCP 拨测：RTT、连接失败率、连接数占比 | I21: 10 | J21: 控制台 | K21: D4 | L21: 人员B | M21: 链路不健康时必须阻止 GTM 接管到备 region
C23: 重申红线：新加坡【不部署 RDS PostgreSQL】。备 region 仅通过公网 TLS（verify-full + IP 白名单）读写马尼拉主库，仅故障接管时生效，不做双写、不建 DTS 链路。

Sheet 网络与安全规划
A1: 网络、安全组、EIP 与凭据规划
A3: 站点 | B3: 地域 / 可用区 | C3: 资源 | D3: 规划值 | E3: 用途 / 说明 | F3: 备注
A4: 马尼拉 | B4: ap-southeast-6 | C4: VPC CIDR | D4: 10.0.0.0/16 | E4: 菲律宾主站点网络 | F4: 与新加坡不重叠
A5: 马尼拉 | B5: 可用区 A | C5: vSwitch | D5: vsw-mnl-pub-a 10.0.0.0/24 | E5: ALB 公共子网 | F5: —
A6: 马尼拉 | B6: 可用区 B | C6: vSwitch | D6: vsw-mnl-pub-b 10.0.1.0/24 | E6: ALB 公共子网 | F6: 多可用区
A7: 马尼拉 | B7: 可用区 A | C7: vSwitch | D7: vsw-mnl-app-a 10.0.16.0/20 | E7: ACK Pod 私有子网 | F7: —
A8: 马尼拉 | B8: 可用区 B | C8: vSwitch | D8: vsw-mnl-app-b 10.0.32.0/20 | E8: ACK Pod 私有子网 | F8: —
A9: 马尼拉 | B9: 可用区 A | C9: vSwitch | D9: vsw-mnl-data-a 10.0.48.0/20 | E9: RDS / Tair / ClickHouse | F9: 数据库不暴露公网子网
A10: 马尼拉 | B10: 可用区 B | C10: vSwitch | D10: vsw-mnl-data-b 10.0.64.0/20 | E10: RDS 备实例 | F10: 主备跨可用区
A11: 新加坡 | B11: ap-southeast-1 | C11: VPC CIDR | D11: 10.1.0.0/16 | E11: 备 region 网络（不含数据库） | F11: 与马尼拉不重叠
A12: 新加坡 | B12: 可用区 A | C12: vSwitch | D12: vsw-sg-pub-a 10.1.0.0/24 | E12: ALB 与 NAT | F12: —
A13: 新加坡 | B13: 可用区 A | C13: vSwitch | D13: vsw-sg-app-a 10.1.16.0/20 | E13: PH 备 Pod | F13: —
A14: 新加坡 | B14: 可用区 B | C14: vSwitch | D14: vsw-sg-app-b 10.1.32.0/20 | E14: PH 备 Pod | F14: 跨 2 个可用区
A16: EIP 规划
A17: 站点 | B17: 用途 | C17: 数量 | D17: 绑定对象 | E17: 说明 | F17: 备注
A18: 马尼拉 | B18: 上游出口白名单池 | C18: 4 | D18: NAT 网关 | E18: 提交给 OpenAI / Anthropic / Google 等供应商做 IP 白名单 | F18: 同一池同时用于 GA 回源
A19: 马尼拉 | B19: ALB 公网地址 | C19: 1 | D19: ALB | E19: 由 ALB 自动分配，用于 GTM 地址池与 DNS 解析 | F19: —
A20: 新加坡 | B20: 上游出口 + RDS 白名单池 | C20: 4 | D20: NAT 网关 | E20: 既用于供应商白名单，也必须加入马尼拉 RDS 公网白名单 | F20: 仅放行该 EIP，禁止 0.0.0.0/0
A22: 安全组规则（最小开放原则）
A23: 站点 | B23: 安全组 | C23: 方向 | D23: 协议 / 端口 | E23: 源 / 目的 | F23: 说明
A24: 马尼拉 | B24: sg-mnl-alb | C24: 入 | D24: TCP 443 / 80 | E24: 0.0.0.0/0 | F24: 终端用户与 WAF 回源；80 仅用于 301 跳转 HTTPS
A25: 马尼拉 | B25: sg-mnl-app | C25: 入 | D25: TCP 3000 | E25: sg-mnl-alb | F25: 仅 ALB 可访问 Pod，禁止内网其他来源
A26: 马尼拉 | B26: sg-mnl-app | C26: 出 | D26: TCP 5432 / 6379 / 9000 | E26: sg-mnl-db | F26: 访问 RDS、Tair、ClickHouse
A27: 马尼拉 | B27: sg-mnl-app | C27: 出 | D27: TCP 443 | E27: 0.0.0.0/0 经 NAT | F27: 调用上游 AI 供应商
A28: 马尼拉 | B28: sg-mnl-db | C28: 入 | D28: TCP 5432 | E28: sg-mnl-app + 新加坡 NAT EIP | F28: 主站点走内网；备 region 走公网且仅白名单 EIP
A29: 新加坡 | B29: sg-sg-alb | C29: 入 | D29: TCP 443 / 80 | E29: 0.0.0.0/0 | F29: GTM 接管时的备 region 入口
A30: 新加坡 | B30: sg-sg-app | C30: 入 | D30: TCP 3000 | E30: sg-sg-alb | F30: 与主站点一致
A31: 新加坡 | B31: sg-sg-app | C31: 出 | D31: TCP 5432 | E31: 马尼拉 RDS 公网地址 | F31: 仅接管期写入；强制 TLS verify-full
A33: 凭据与密钥（KMS 托管，禁止落库落 Git）
A34: 凭据 | B34: 载体 | C34: 使用方 | D34: 轮换周期 | E34: 说明 | F34: 备注
A35: SQL_DSN | B35: KMS 凭据管家 | C35: 马尼拉 / 新加坡备应用 | D35: 90 天 | E35: 含数据库账号密码；备 region 使用公网地址 + verify-full | F35: 轮换需两站点同步
A36: REDIS_CONN_STRING | B36: KMS 凭据管家 | C36: 马尼拉 / 新加坡备应用 | D36: 90 天 | E36: Tair 连接串 | F36: 各站点使用各自实例
A37: SESSION_SECRET | B37: KMS 凭据管家 | C37: 全部站点 | D37: 180 天 | E37: 必须全区域全实例一致 | F37: 不一致会导致切换后会话全部失效
A38: RDS CA 证书 | B38: 镜像只读路径 /etc/ssl/rds-ca.pem | C38: 新加坡备 region | D38: 随证书更新 | E38: 用于 sslmode=verify-full 校验 | F38: 禁止使用 require/disable
A39: 支付渠道密钥 | B39: KMS 凭据管家 | C39: 马尼拉应用 | D39: 按渠道要求 | E39: 支付回调与退款 | F39: 回调路径需在 WAF 放行

Sheet 落地计划
A1: 落地计划 · 2 人全职 / 5 天 / 10 个时段（日期由「说明与总览」D1 日期自动推算）
A3: 天 | B3: 序号 | C3: 任务 / 交付物 | D3: 负责 | E3: 前置依赖 | F3: 工期(人时) | G3: 起始时段 | H3: 完成时段 | I3: 日期 | J3: D1上午 | K3: D1下午 | L3: D2上午 | M3: D2下午 | N3: D3上午 | O3: D3下午 | P3: D4上午 | Q3: D4下午 | R3: D5上午 | S3: D5下午 | T3: 验收标准 | U3: 状态 | V3: 每时段投入(人时)
A4: D1 | B4: 1 | C4: 账号/实名/配额/支付最终确认与补件（门禁 G0 收口） | D4: 人员A | E4: G1–G8 | F4: 2 | G4: 1 | H4: 1 | I4: ==说明与总览!$B$19+VALUE(MID($A4,2,1))-1 -> 46287 | J4: ==IF(AND($G4<=1,$H4>=1),"■■","") -> ■■ | K4: ==IF(AND($G4<=2,$H4>=2),"■■","") | L4: ==IF(AND($G4<=3,$H4>=3),"■■","") | M4: ==IF(AND($G4<=4,$H4>=4),"■■","") | N4: ==IF(AND($G4<=5,$H4>=5),"■■","") | O4: ==IF(AND($G4<=6,$H4>=6),"■■","") | P4: ==IF(AND($G4<=7,$H4>=7),"■■","") | Q4: ==IF(AND($G4<=8,$H4>=8),"■■","") | R4: ==IF(AND($G4<=9,$H4>=9),"■■","") | S4: ==IF(AND($G4<=10,$H4>=10),"■■","") | T4: G0 门禁全部通过，无遗留待批复项 | U4: 未开始 | V4: ==IF($H4<$G4,0,$F4/($H4-$G4+1)) -> 2
A5: D1 | B5: 2 | C5: 域名解析记录与 NS 生效复核 | D5: 人员B | E5: G4,G5 | F5: 1 | G5: 1 | H5: 1 | I5: ==说明与总览!$B$19+VALUE(MID($A5,2,1))-1 -> 46287 | J5: ==IF(AND($G5<=1,$H5>=1),"■■","") -> ■■ | K5: ==IF(AND($G5<=2,$H5>=2),"■■","") | L5: ==IF(AND($G5<=3,$H5>=3),"■■","") | M5: ==IF(AND($G5<=4,$H5>=4),"■■","") | N5: ==IF(AND($G5<=5,$H5>=5),"■■","") | O5: ==IF(AND($G5<=6,$H5>=6),"■■","") | P5: ==IF(AND($G5<=7,$H5>=7),"■■","") | Q5: ==IF(AND($G5<=8,$H5>=8),"■■","") | R5: ==IF(AND($G5<=9,$H5>=9),"■■","") | S5: ==IF(AND($G5<=10,$H5>=10),"■■","") | T5: dig 权威解析生效，解析记录无冲突 | U5: 未开始 | V5: ==IF($H5<$G5,0,$F5/($H5-$G5+1)) -> 1
A6: D1 | B6: 3 | C6: SSL 证书部署到 ALB / WAF / DCDN（配置就绪） | D6: 人员B | E6: G6 | F6: 1 | G6: 1 | H6: 1 | I6: ==说明与总览!$B$19+VALUE(MID($A6,2,1))-1 -> 46287 | J6: ==IF(AND($G6<=1,$H6>=1),"■■","") -> ■■ | K6: ==IF(AND($G6<=2,$H6>=2),"■■","") | L6: ==IF(AND($G6<=3,$H6>=3),"■■","") | M6: ==IF(AND($G6<=4,$H6>=4),"■■","") | N6: ==IF(AND($G6<=5,$H6>=5),"■■","") | O6: ==IF(AND($G6<=6,$H6>=6),"■■","") | P6: ==IF(AND($G6<=7,$H6>=7),"■■","") | Q6: ==IF(AND($G6<=8,$H6>=8),"■■","") | R6: ==IF(AND($G6<=9,$H6>=9),"■■","") | S6: ==IF(AND($G6<=10,$H6>=10),"■■","") | T6: 证书链校验通过，TLS 1.2/1.3 可用 | U6: 未开始 | V6: ==IF($H6<$G6,0,$F6/($H6-$G6+1)) -> 1
A7: D1 | B7: 4 | C7: 创建马尼拉 RDS PostgreSQL 高可用版（主备跨 AZ）+ 参数组 | D7: 人员B | E7: G2,G3 | F7: 2 | G7: 1 | H7: 1 | I7: ==说明与总览!$B$19+VALUE(MID($A7,2,1))-1 -> 46287 | J7: ==IF(AND($G7<=1,$H7>=1),"■■","") -> ■■ | K7: ==IF(AND($G7<=2,$H7>=2),"■■","") | L7: ==IF(AND($G7<=3,$H7>=3),"■■","") | M7: ==IF(AND($G7<=4,$H7>=4),"■■","") | N7: ==IF(AND($G7<=5,$H7>=5),"■■","") | O7: ==IF(AND($G7<=6,$H7>=6),"■■","") | P7: ==IF(AND($G7<=7,$H7>=7),"■■","") | Q7: ==IF(AND($G7<=8,$H7>=8),"■■","") | R7: ==IF(AND($G7<=9,$H7>=9),"■■","") | S7: ==IF(AND($G7<=10,$H7>=10),"■■","") | T7: 实例可连、主备跨可用区、参数组生效 | U7: 未开始 | V7: ==IF($H7<$G7,0,$F7/($H7-$G7+1)) -> 2
A8: D1 | B8: 5 | C8: 创建马尼拉 VPC 与 4 组 vSwitch（跨 2 AZ） | D8: 人员A | E8: G1,G2 | F8: 4 | G8: 1 | H8: 2 | I8: ==说明与总览!$B$19+VALUE(MID($A8,2,1))-1 -> 46287 | J8: ==IF(AND($G8<=1,$H8>=1),"■■","") -> ■■ | K8: ==IF(AND($G8<=2,$H8>=2),"■■","") -> ■■ | L8: ==IF(AND($G8<=3,$H8>=3),"■■","") | M8: ==IF(AND($G8<=4,$H8>=4),"■■","") | N8: ==IF(AND($G8<=5,$H8>=5),"■■","") | O8: ==IF(AND($G8<=6,$H8>=6),"■■","") | P8: ==IF(AND($G8<=7,$H8>=7),"■■","") | Q8: ==IF(AND($G8<=8,$H8>=8),"■■","") | R8: ==IF(AND($G8<=9,$H8>=9),"■■","") | S8: ==IF(AND($G8<=10,$H8>=10),"■■","") | T8: 网段与「网络与安全规划」完全一致 | U8: 未开始 | V8: ==IF($H8<$G8,0,$F8/($H8-$G8+1)) -> 2
A9: D1 | B9: 6 | C9: 创建马尼拉 NAT 网关与上游出口 EIP 池 | D9: 人员A | E9: 5 | F9: 2 | G9: 2 | H9: 2 | I9: ==说明与总览!$B$19+VALUE(MID($A9,2,1))-1 -> 46287 | J9: ==IF(AND($G9<=1,$H9>=1),"■■","") | K9: ==IF(AND($G9<=2,$H9>=2),"■■","") -> ■■ | L9: ==IF(AND($G9<=3,$H9>=3),"■■","") | M9: ==IF(AND($G9<=4,$H9>=4),"■■","") | N9: ==IF(AND($G9<=5,$H9>=5),"■■","") | O9: ==IF(AND($G9<=6,$H9>=6),"■■","") | P9: ==IF(AND($G9<=7,$H9>=7),"■■","") | Q9: ==IF(AND($G9<=8,$H9>=8),"■■","") | R9: ==IF(AND($G9<=9,$H9>=9),"■■","") | S9: ==IF(AND($G9<=10,$H9>=10),"■■","") | T9: EIP 固定且可正常出网 | U9: 未开始 | V9: ==IF($H9<$G9,0,$F9/($H9-$G9+1)) -> 2
A10: D1 | B10: 7 | C10: 创建 Tair 主备版实例 | D10: 人员B | E10: 4 | F10: 1 | G10: 2 | H10: 2 | I10: ==说明与总览!$B$19+VALUE(MID($A10,2,1))-1 -> 46287 | J10: ==IF(AND($G10<=1,$H10>=1),"■■","") | K10: ==IF(AND($G10<=2,$H10>=2),"■■","") -> ■■ | L10: ==IF(AND($G10<=3,$H10>=3),"■■","") | M10: ==IF(AND($G10<=4,$H10>=4),"■■","") | N10: ==IF(AND($G10<=5,$H10>=5),"■■","") | O10: ==IF(AND($G10<=6,$H10>=6),"■■","") | P10: ==IF(AND($G10<=7,$H10>=7),"■■","") | Q10: ==IF(AND($G10<=8,$H10>=8),"■■","") | R10: ==IF(AND($G10<=9,$H10>=9),"■■","") | S10: ==IF(AND($G10<=10,$H10>=10),"■■","") | T10: 连接与 ACL 认证验证通过 | U10: 未开始 | V10: ==IF($H10<$G10,0,$F10/($H10-$G10+1)) -> 1
A11: D1 | B11: 8 | C11: 创建 OSS Bucket（ZRS + 版本控制 + 生命周期） | D11: 人员B | E11: G7 | F11: 1 | G11: 2 | H11: 2 | I11: ==说明与总览!$B$19+VALUE(MID($A11,2,1))-1 -> 46287 | J11: ==IF(AND($G11<=1,$H11>=1),"■■","") | K11: ==IF(AND($G11<=2,$H11>=2),"■■","") -> ■■ | L11: ==IF(AND($G11<=3,$H11>=3),"■■","") | M11: ==IF(AND($G11<=4,$H11>=4),"■■","") | N11: ==IF(AND($G11<=5,$H11>=5),"■■","") | O11: ==IF(AND($G11<=6,$H11>=6),"■■","") | P11: ==IF(AND($G11<=7,$H11>=7),"■■","") | Q11: ==IF(AND($G11<=8,$H11>=8),"■■","") | R11: ==IF(AND($G11<=9,$H11>=9),"■■","") | S11: ==IF(AND($G11<=10,$H11>=10),"■■","") | T11: 策略与防盗链规则生效 | U11: 未开始 | V11: ==IF($H11<$G11,0,$F11/($H11-$G11+1)) -> 1
A12: D1 | B12: 9 | C12: 创建 ClickHouse 2 节点日志库（TTL 90 天） | D12: 人员B | E12: G7 | F12: 2 | G12: 2 | H12: 2 | I12: ==说明与总览!$B$19+VALUE(MID($A12,2,1))-1 -> 46287 | J12: ==IF(AND($G12<=1,$H12>=1),"■■","") | K12: ==IF(AND($G12<=2,$H12>=2),"■■","") -> ■■ | L12: ==IF(AND($G12<=3,$H12>=3),"■■","") | M12: ==IF(AND($G12<=4,$H12>=4),"■■","") | N12: ==IF(AND($G12<=5,$H12>=5),"■■","") | O12: ==IF(AND($G12<=6,$H12>=6),"■■","") | P12: ==IF(AND($G12<=7,$H12>=7),"■■","") | Q12: ==IF(AND($G12<=8,$H12>=8),"■■","") | R12: ==IF(AND($G12<=9,$H12>=9),"■■","") | S12: ==IF(AND($G12<=10,$H12>=10),"■■","") | T12: 写入成功且 TTL 生效 | U12: 未开始 | V12: ==IF($H12<$G12,0,$F12/($H12-$G12+1)) -> 2
A13: D2 | B13: 10 | C13: 创建马尼拉 ACK Pro 集群（K8s 1.31 + Terway + RRSA） | D13: 人员A | E13: 5,6 | F13: 2 | G13: 3 | H13: 3 | I13: ==说明与总览!$B$19+VALUE(MID($A13,2,1))-1 -> 46288 | J13: ==IF(AND($G13<=1,$H13>=1),"■■","") | K13: ==IF(AND($G13<=2,$H13>=2),"■■","") | L13: ==IF(AND($G13<=3,$H13>=3),"■■","") -> ■■ | M13: ==IF(AND($G13<=4,$H13>=4),"■■","") | N13: ==IF(AND($G13<=5,$H13>=5),"■■","") | O13: ==IF(AND($G13<=6,$H13>=6),"■■","") | P13: ==IF(AND($G13<=7,$H13>=7),"■■","") | Q13: ==IF(AND($G13<=8,$H13>=8),"■■","") | R13: ==IF(AND($G13<=9,$H13>=9),"■■","") | S13: ==IF(AND($G13<=10,$H13>=10),"■■","") | T13: 集群 Running，RRSA 可获取临时凭据 | U13: 未开始 | V13: ==IF($H13<$G13,0,$F13/($H13-$G13+1)) -> 2
A14: D2 | B14: 11 | C14: 创建 ECS 节点池 4×g8i.2xlarge（跨 2 AZ、ESSD、nofile 调优） | D14: 人员A | E14: 10 | F14: 4 | G14: 3 | H14: 4 | I14: ==说明与总览!$B$19+VALUE(MID($A14,2,1))-1 -> 46288 | J14: ==IF(AND($G14<=1,$H14>=1),"■■","") | K14: ==IF(AND($G14<=2,$H14>=2),"■■","") | L14: ==IF(AND($G14<=3,$H14>=3),"■■","") -> ■■ | M14: ==IF(AND($G14<=4,$H14>=4),"■■","") -> ■■ | N14: ==IF(AND($G14<=5,$H14>=5),"■■","") | O14: ==IF(AND($G14<=6,$H14>=6),"■■","") | P14: ==IF(AND($G14<=7,$H14>=7),"■■","") | Q14: ==IF(AND($G14<=8,$H14>=8),"■■","") | R14: ==IF(AND($G14<=9,$H14>=9),"■■","") | S14: ==IF(AND($G14<=10,$H14>=10),"■■","") | T14: 节点 Ready 且跨 2 个可用区分布 | U14: 未开始 | V14: ==IF($H14<$G14,0,$F14/($H14-$G14+1)) -> 2
A15: D2 | B15: 12 | C15: 创建新加坡 VPC + vSwitch + NAT 网关 + EIP 池 | D15: 人员A | E15: 5,6 | F15: 2 | G15: 4 | H15: 4 | I15: ==说明与总览!$B$19+VALUE(MID($A15,2,1))-1 -> 46288 | J15: ==IF(AND($G15<=1,$H15>=1),"■■","") | K15: ==IF(AND($G15<=2,$H15>=2),"■■","") | L15: ==IF(AND($G15<=3,$H15>=3),"■■","") | M15: ==IF(AND($G15<=4,$H15>=4),"■■","") -> ■■ | N15: ==IF(AND($G15<=5,$H15>=5),"■■","") | O15: ==IF(AND($G15<=6,$H15>=6),"■■","") | P15: ==IF(AND($G15<=7,$H15>=7),"■■","") | Q15: ==IF(AND($G15<=8,$H15>=8),"■■","") | R15: ==IF(AND($G15<=9,$H15>=9),"■■","") | S15: ==IF(AND($G15<=10,$H15>=10),"■■","") | T15: 新加坡 EIP 固定可出网 | U15: 未开始 | V15: ==IF($H15<$G15,0,$F15/($H15-$G15+1)) -> 2
... A42: D5 | B42: 39 | C42: 备 region 链路拨测与告警（不健康时阻止 GTM 接管） | D42: 人员B | E42: 30 | F42: 2 | G42: 10 | H42: 10 | I42: ==说明与总览!$B$19+VALUE(MID($A42,2,1))-1 -> 46291 | J42: ==IF(AND($G42<=1,$H42>=1),"■■","") | K42: ==IF(AND($G42<=2,$H42>=2),"■■","") | L42: ==IF(AND($G42<=3,$H42>=3),"■■","") | M42: ==IF(AND($G42<=4,$H42>=4),"■■","") | N42: ==IF(AND($G42<=5,$H42>=5),"■■","") | O42: ==IF(AND($G42<=6,$H42>=6),"■■","") | P42: ==IF(AND($G42<=7,$H42>=7),"■■","") | Q42: ==IF(AND($G42<=8,$H42>=8),"■■","") | R42: ==IF(AND($G42<=9,$H42>=9),"■■","") | S42: ==IF(AND($G42<=10,$H42>=10),"■■","") -> ■■ | T42: 链路异常可告警并阻断接管 | U42: 未开始 | V42: ==IF($H42<$G42,0,$F42/($H42-$G42+1)) -> 2
A45: 人力负荷校验（每时段单人上限 4 人时） | J45: S1 | K45: S2 | L45: S3 | M45: S4 | N45: S5 | O45: S6 | P45: S7 | Q45: S8 | R45: S9 | S45: S10
A46: 人员A | J46: ==SUMIFS($V$4:$V$42,$D$4:$D$42,"人员A",$G$4:$G$42,"<=1",$H$4:$H$42,">=1") -> 4 | K46: ==SUMIFS($V$4:$V$42,$D$4:$D$42,"人员A",$G$4:$G$42,"<=2",$H$4:$H$42,">=2") -> 4 | L46: ==SUMIFS($V$4:$V$42,$D$4:$D$42,"人员A",$G$4:$G$42,"<=3",$H$4:$H$42,">=3") -> 4 | M46: ==SUMIFS($V$4:$V$42,$D$4:$D$42,"人员A",$G$4:$G$42,"<=4",$H$4:$H$42,">=4") -> 4 | N46: ==SUMIFS($V$4:$V$42,$D$4:$D$42,"人员A",$G$4:$G$42,"<=5",$H$4:$H$42,">=5") -> 4 | O46: ==SUMIFS($V$4:$V$42,$D$4:$D$42,"人员A",$G$4:$G$42,"<=6",$H$4:$H$42,">=6") -> 4 | P46: ==SUMIFS($V$4:$V$42,$D$4:$D$42,"人员A",$G$4:$G$42,"<=7",$H$4:$H$42,">=7") -> 4 | Q46: ==SUMIFS($V$4:$V$42,$D$4:$D$42,"人员A",$G$4:$G$42,"<=8",$H$4:$H$42,">=8") -> 4 | R46: ==SUMIFS($V$4:$V$42,$D$4:$D$42,"人员A",$G$4:$G$42,"<=9",$H$4:$H$42,">=9") -> 4 | S46: ==SUMIFS($V$4:$V$42,$D$4:$D$42,"人员A",$G$4:$G$42,"<=10",$H$4:$H$42,">=10") -> 4
A47: 人员B | J47: ==SUMIFS($V$4:$V$42,$D$4:$D$42,"人员B",$G$4:$G$42,"<=1",$H$4:$H$42,">=1") -> 4 | K47: ==SUMIFS($V$4:$V$42,$D$4:$D$42,"人员B",$G$4:$G$42,"<=2",$H$4:$H$42,">=2") -> 4 | L47: ==SUMIFS($V$4:$V$42,$D$4:$D$42,"人员B",$G$4:$G$42,"<=3",$H$4:$H$42,">=3") -> 4 | M47: ==SUMIFS($V$4:$V$42,$D$4:$D$42,"人员B",$G$4:$G$42,"<=4",$H$4:$H$42,">=4") -> 4 | N47: ==SUMIFS($V$4:$V$42,$D$4:$D$42,"人员B",$G$4:$G$42,"<=5",$H$4:$H$42,">=5") -> 4 | O47: ==SUMIFS($V$4:$V$42,$D$4:$D$42,"人员B",$G$4:$G$42,"<=6",$H$4:$H$42,">=6") -> 4 | P47: ==SUMIFS($V$4:$V$42,$D$4:$D$42,"人员B",$G$4:$G$42,"<=7",$H$4:$H$42,">=7") -> 4 | Q47: ==SUMIFS($V$4:$V$42,$D$4:$D$42,"人员B",$G$4:$G$42,"<=8",$H$4:$H$42,">=8") -> 4 | R47: ==SUMIFS($V$4:$V$42,$D$4:$D$42,"人员B",$G$4:$G$42,"<=9",$H$4:$H$42,">=9") -> 4 | S47: ==SUMIFS($V$4:$V$42,$D$4:$D$42,"人员B",$G$4:$G$42,"<=10",$H$4:$H$42,">=10") -> 4
A48: 负荷结论 | J48: ==IF(COUNTIF(J5:S6,">4")>0,"存在超载时段，需调整排期","负荷均衡：每人每时段 ≤ 4 人时") -> 负荷均衡：每人每时段 ≤ 4 人时
A49: 总投入(人时) / 总产能(人时，2 人 × 5 天 × 8 小时) | J49: ==SUM(F4:F42) -> 80 | K49: ==2*5*8 -> 80 | L49: ==IF(J49<=K49,"工期可行：总投入未超 2 人 × 5 天产能","超出产能，须延长工期或裁剪范围") -> 工期可行：总投入未超 2 人 × 5 天产能
A51: T-3 前置门禁清单（等待型，不占用 5 天工期人力；G1–G8 全部完成才允许 D1 启动）
A52: 编号 | B52: 前置事项 | C52: 类别 | D52: 负责角色 | E52: 发起时点 | F52: 最长等待 | G52: 门禁作用
A53: G1 | B53: 注册阿里云国际站账号并发起企业实名认证 | C53: 账号 | D53: 项目负责人 | E53: T-3（2026-09-22） | F53: 1–2 工作日 | G53: 未实名无法购买 ECS/RDS，直接阻塞 D1
A54: G2 | B54: 提交资源配额工单（ECS vCPU / EIP / ALB / RDS / GTM） | C54: 配额 | D54: 运维负责人 | E54: T-3 | F54: 2–3 工作日 | G54: 未批复无法创建节点池与出口 EIP
A55: G3 | B55: 开通后付费、绑定支付方式、设置预算告警 | C55: 账号 | D55: 财务 | E55: T-3 | F55: 当日 | G55: 未开通无法下单
A56: G4 | B56: 域名注册 + 实名认证 + NS 指向云解析 | C56: 域名 | D56: 项目负责人 | E56: T-3 | F56: 24–48h 生效 | G56: NS 未生效则 D1 接入层无法验证
A57: G5 | B57: SSL 通配符证书申请 | C57: 证书 | D57: 运维负责人 | E57: T-3 | F57: 1–24h | G57: 无证书则 ALB/WAF HTTPS 不可用
A58: G6 | B58: 证书部署到 ALB / WAF / DCDN 的准备（域名与配置模板） | C58: 证书 | D58: 运维负责人 | E58: T-3 | F58: 当日 | G58: D1 上午需直接验证
A59: G7 | B59: 开通全部云产品（网络/计算/数据/接入/观测） | C59: 产品 | D59: 运维负责人 | E59: T-3 | F59: 当日 | G59: 国际站需逐产品开通，未开通则无法下单
A60: G8 | B60: 代码侧补建项排期确认：/healthz、/readyz、/metrics、限流降级改造 | C60: 研发 | D60: 后端负责人 | E60: T-3 | F60: 1–2 工作日 | G60: 未完成则探针与监控降级使用临时方案，且 Tair 故障会 fail-closed
A61: G9 | B61: RAM 用户 / 资源组 / 成本标签 / MFA / ActionTrail 预建 | C61: 账号 | D61: 安全负责人 | E61: T-3 | F61: 当日 | G61: 最小权限与审计是上线检查表必查项
A62: G0 门禁：以上 G1–G9 任一项未完成，D1 不得启动；5 天工期为「2 人全职 + 前置项全部就绪」的乐观口径，无缓冲日。

Sheet 里程碑与验收
A1: 里程碑门禁、验收证据、关键风险与工期裁剪预案
A3: 里程碑 | B3: 偏移(日，D1=0) | C3: 目标日期 | D3: 通过标准 | E3: 验收证据 | F3: 负责角色 | G3: 状态 | H3: 备注
A4: G0 前置门禁通过 | B4: -3 | C4: 46287 | D4: T-3 前置清单 G1–G9 全部完成，账号可下单、配额已批复、域名 NS 生效、证书已签发 | E4: 实名认证截图、配额批复工单号、dig NS 结果、证书 ID | F4: 项目负责人 | G4: 未开始 | H4: 未通过则 5 天工期不可达，必须顺延
A5: M1 D1 结束：合规与数据底座就绪 | B5: 1 | C5: ==说明与总览!$B$19+B5 -> 46288 | D5: 账号合规收口、马尼拉网络底座可用、RDS/Tair/ClickHouse/OSS 已创建 | E5: VPC/EIP 清单、RDS 实例详情、Tair 与 CH 连接测试记录 | F5: 人员A / 人员B | G5: 未开始 | H5: RDS 主备跨可用区
A6: M2 D2 结束：计算底座与主库就绪 | B6: 1 | C6: ==说明与总览!$B$19+B6 -> 46288 | D6: ACK 集群与 4 节点 Ready、RDS 账号与备份策略生效、双地域 ACR 可拉取镜像、master 迁移幂等 | E6: 节点列表、RDS 备份列表、镜像拉取记录、迁移两次的幂等验证记录 | F6: 人员A / 人员B | G6: 未开始 | H6: master 迁移必须连续两次结果一致
A7: M3 D3 结束：接入层打通且主站点可灰度 | B7: 2 | C7: ==说明与总览!$B$19+B7 -> 46289 | D7: ALB/WAF/GTM 生效、stable 4 副本跨 AZ、安全组与白名单核对通过 | E7: ALB 健康检查截图、WAF 拦截记录、Pod 跨 AZ 分布截图、安全组核对表 | F7: 人员A / 人员B | G7: 未开始 | H7: 此时系统已可对外提供服务（仅主站点）
A8: M4 D4 结束：备 region 接管可用且可观测就绪 | B8: 3 | C8: ==说明与总览!$B$19+B8 -> 46290 | D8: 备 region 公网读写马尼拉主库成功（RTT ≤ 70ms）、PH 备 2 副本 Ready、SLS/ARMS/拨测可见、canary 权重可用 | E8: 连接测试记录（含 sslmode=verify-full）、Pod 配置截图、拨测报表、看板截图 | F8: 人员A / 人员B | G8: 未开始 | H8: RTT > 100ms 或失败率 > 0.1% 时暂不挂入 GTM
A9: M5 D5 结束：演练通过、正式上线并完成移交 | B9: 4 | C9: ==说明与总览!$B$19+B9 -> 46291 | D9: 备 region 接管与主库切换演练通过、压测达标、安全核查无高危项、上线检查表通过 | E9: 演练报告（含 RTO/RPO）、压测报告、安全核查清单、上线检查表、Runbook | F9: 人员A / 人员B | G9: 未开始 | H9: 上线后 1 小时值守观察
A11: 关键风险与前置依赖（2 人 / 5 天口径）
A12: 风险 / 前置依赖 | B12: 影响 | C12: 应对措施 | D12: 责任角色 | E12: 触发信号 | F12: 新增风险等级 | G12: 剩余风险 | H12: 备注
A13: 企业实名认证或配额审批未在 T-3 完成 | B13: 5 天工期直接不可达，全案顺延 | C13: T-3 上午立即提交；每日 18:00 跟进工单；先用已批复配额创建 VPC/ALB 等低配额资源 | D13: 项目负责人 | E13: T-3 日落前未通过 / 未批复 | F13: 高 | G13: 工期顺延 2–3 天 | H13: 唯一的外部不可控项
A14: 仅 2 人且无人员冗余 | B14: 任一人阻塞或请假，关键路径断裂导致整体延期 | C14: 明确 A/B 分工并互备关键命令；每日 15 分钟站会同步阻碍项；预留每日 1 小时加班缓冲 | D14: 项目负责人 | E14: 单日任务完成率 < 80% | F14: 高 | G14: 需临时补充第三人 | H14: A 负责网络/接入，B 负责数据/应用
A15: 域名 NS 生效需 24–48 小时 | B15: D1 接入层无法验证，顺延 D3 | C15: T-3 完成 NS 托管并 dig 验证；未生效前先用 ALB 默认域名完成配置验证 | D15: 运维负责人 | E15: dig 返回非阿里云 DNS | F15: 中 | G15: 顺延 1 天 | H15: 已在 G4 列为门禁
A16: 代码侧补建项未完成（/healthz、/readyz、/metrics、限流降级） | B16: 探针不准确、监控缺失、Tair 故障时 fail-closed 直接 5xx | C16: T-3 前完成排期与代码合并；未完成时探针临时用 /api/status 与 TCP，限流降级列为上线后首周必办项 | D16: 后端负责人 | E16: D2 部署时探针仍指向 /api/status | F16: 高 | G16: 可用性指标置信度下降 | H16: 属已知缺口，非本次部署可闭环
A17: 新加坡 → 马尼拉 RDS 公网延迟或抖动 | B17: 备 region 接管期写延迟抬升，影响体感 | C17: D4 完成实测并留存基线；RTT > 100ms 或失败率 > 0.1% 时暂不把备 region 挂入 GTM 备地址池 | D17: 人员B | E17: 拨测 RTT 超标 | F17: 中 | G17: 接管期写入 P99 抬升 ≤ 80ms | H17: 链路不健康时阻断接管
A18: 备 region 误以 master 启动导致并发迁移同一 schema | B18: 迁移冲突、锁表甚至数据损坏 | C18: 备 region 固定 NODE_TYPE=slave 并纳入部署门禁校验；备 region 不授予迁移权限账号 | D18: 人员B | E18: 备 region 日志出现 AutoMigrate | F18: 中 | G18: 可控（门禁拦截） | H18: 红线项
A19: 双写风险（主站点与备 region 同时写同一主库） | B19: 计费对账分裂、额度超扣或重复扣 | C19: GTM 健康探测 + 主站点 ALB 摘流共同收口；禁止本地库、只读副本与 DTS 链路；D5 接管演练验证 | D19: 人员A | E19: 同一 request_id 出现双写记录 | F19: 中 | G19: 可控（架构层面消除） | H19: 红线项
A20: 5 天无缓冲，D5 演练发现问题无修复窗口 | B20: 上线延期或带缺陷上线 | C20: 将 D5 的演练与上线设为可顺延日；必要时按下方裁剪预案降级交付范围 | D20: 项目负责人 | E20: D4 结束仍有 M4 未通过项 | F20: 高 | G20: 延期 1 天或降级交付 | H20: 建议预留 D6 作为缓冲日
A21: 成本超预算（出站带宽与 ALB LCU 为主要变量） | B21: 需追加预算或降配 | C21: 成本标签 + 预算告警；备 region 采用冷备形态（副本置 0 + GTM 触发扩容）显著降低常态成本 | D21: 财务 | E21: 月度账单达到预算 80% | F21: 低 | G21: RTO 由秒级变为分钟级 | H21: —
A23: 工期裁剪预案（按以下顺序降级，优先保主站点可上线）
A24: 顺序 | B24: 裁剪项 | C24: 触发条件 | D24: 影响 | E24: 决策人 | F24: 是否影响 SLA | G24: 可否上线后补齐 | H24: 备注
A25: 1 | B25: DCDN 静态加速延后至上线后 | C25: D2 工期紧张 | D25: 静态资源不经 CDN，首屏略慢 | E25: 项目负责人 | F25: 否 | G25: 可 | H25: 改动最小
A26: 2 | B26: RDS 只读实例取消 | C26: 成本或工期紧张 | D26: 报表查询与主库争用 | E26: 人员B | F26: 否 | G26: 可 | H26: —
A27: 3 | B27: 备 region 本地 ClickHouse 暂用主站点 ClickHouse | C27: D4 工期紧张 | D27: 备 region 日志跨区写入，接管期略慢 | E27: 人员B | F27: 否 | G27: 可 | H27: 不影响主链路
A28: 4 | B28: 压测验收缩短为关键场景抽测 | C28: D5 时间不足 | D28: 容量结论置信度下降 | E28: 人员A | F28: 否 | G28: 可 | H28: 需上线后一周内补测
A29: 5 | B29: 备 region 热备（2 副本）改为冷备（0 副本 + GTM 触发扩容） | C29: 成本优先 | D29: 接管 RTO 由秒级变为分钟级 | E29: 项目负责人 | F29: 是（RTO 变长） | G29: 可 | H29: 可用性仍满足 99.95% 但切换体验下降
A30: 6 | B30: 备 region 整体延后至上线后第 2 周 | C30: D4 结束仍未打通公网读写 | D30: 失去区域级容灾，SLA 目标不达标 | E30: 项目负责人 | F30: 是（SLA 不达标） | G30: 可 | H30: 最后手段，需书面记录风险
